twinic/__init__.py
twinic/client.py
twinic/server.py
twinic-0.1.0.dist-info/licenses/LICENSE
twinic-0.1.0.dist-info/METADATA
twinic-0.1.0.dist-info/WHEEL
twinic-0.1.0.dist-info/top_level.txt
twinic-0.1.0.dist-info/RECORD
